itree/__init__.py
itree/itree.py
itree-0.0.5.dist-info/LICENSE
itree-0.0.5.dist-info/METADATA
itree-0.0.5.dist-info/WHEEL
itree-0.0.5.dist-info/top_level.txt
itree-0.0.5.dist-info/RECORD
